finance_automl/__init__.py
finance_automl/automl.py
finance_automl/datasplitter.py
finance_automl/deploy_hook.py
finance_automl/ensembler.py
finance_automl/hyperoptimizer.py
finance_automl/metric_engine.py
finance_automl/reportgen.py
finance_automl-0.1.3.dist-info/licenses/LICENSE
finance_automl-0.1.3.dist-info/METADATA
finance_automl-0.1.3.dist-info/WHEEL
finance_automl-0.1.3.dist-info/top_level.txt
finance_automl-0.1.3.dist-info/RECORD
