Metadata-Version: 2.4
Name: finance-automl
Version: 0.1.3
Summary: AutoML framework for financial time-series with leakage prevention and finance-specific metrics.
Home-page: https://github.com/advait27/finautoml
Author: Advait Dharmadhikari
Author-email: advaituni@gmail.com
Classifier: Programming Language :: Python :: 3
Classifier: License :: OSI Approved :: MIT License
Classifier: Operating System :: OS Independent
Requires-Python: >=3.9
License-File: LICENSE
Requires-Dist: pandas>=1.0.0
Requires-Dist: numpy>=1.18.0
Requires-Dist: matplotlib>=3.0.0
Requires-Dist: optuna>=3.0.0
Requires-Dist: scikit-learn>=0.24.0
Requires-Dist: packaging<24,>=16.8
Requires-Dist: docutils<0.19,>=0.14
Dynamic: author
Dynamic: author-email
Dynamic: classifier
Dynamic: description
Dynamic: description-content-type
Dynamic: home-page
Dynamic: license-file
Dynamic: requires-dist
Dynamic: requires-python
Dynamic: summary
